docs/conf.py
docs/favicon.png
docs/utils.py
docs/themes/psychopy_plugin/static/Nottingham Supported.png
docs/themes/psychopy_plugin/static/Psychopy Plugin Header Large.png
docs/themes/psychopy_plugin/static/Psychopy Plugin Header Small.png
psychopy_emotiv/__init__.py
psychopy_emotiv/emotiv.py
psychopy_emotiv/emotiv_marking/__init__.py
psychopy_emotiv/emotiv_marking/classic/emotiv_mark@2x.png
psychopy_emotiv/emotiv_marking/classic/emotiv_marking.png
psychopy_emotiv/emotiv_marking/dark/emotiv_marking.png
psychopy_emotiv/emotiv_marking/dark/emotiv_marking@2x.png
psychopy_emotiv/emotiv_marking/light/emotiv_marking.png
psychopy_emotiv/emotiv_marking/light/emotiv_marking@2x.png
psychopy_emotiv/emotiv_record/__init__.py
psychopy_emotiv/emotiv_record/classic/emotiv_record.png
psychopy_emotiv/emotiv_record/classic/emotiv_record@2x.png
psychopy_emotiv/emotiv_record/dark/emotiv_record.png
psychopy_emotiv/emotiv_record/dark/emotiv_record@2x.png
psychopy_emotiv/emotiv_record/light/emotiv_record.png
psychopy_emotiv/emotiv_record/light/emotiv_record@2x.png
psychopy_emotiv-0.1.2.dist-info/LICENSE
psychopy_emotiv-0.1.2.dist-info/METADATA
psychopy_emotiv-0.1.2.dist-info/WHEEL
psychopy_emotiv-0.1.2.dist-info/entry_points.txt
psychopy_emotiv-0.1.2.dist-info/top_level.txt
psychopy_emotiv-0.1.2.dist-info/RECORD
